odoo/addons/attribute_set_mass_edit/README.rst
odoo/addons/attribute_set_mass_edit/__init__.py
odoo/addons/attribute_set_mass_edit/__manifest__.py
odoo/addons/attribute_set_mass_edit/i18n/attribute_set_mass_edit.pot
odoo/addons/attribute_set_mass_edit/models/__init__.py
odoo/addons/attribute_set_mass_edit/models/attribute_attribute.py
odoo/addons/attribute_set_mass_edit/models/attribute_group.py
odoo/addons/attribute_set_mass_edit/models/ir_actions_server.py
odoo/addons/attribute_set_mass_edit/models/mass_editing_line.py
odoo/addons/attribute_set_mass_edit/readme/CONTRIBUTORS.rst
odoo/addons/attribute_set_mass_edit/readme/DESCRIPTION.rst
odoo/addons/attribute_set_mass_edit/readme/USAGE.rst
odoo/addons/attribute_set_mass_edit/static/description/icon.png
odoo/addons/attribute_set_mass_edit/static/description/index.html
odoo/addons/attribute_set_mass_edit/tests/__init__.py
odoo/addons/attribute_set_mass_edit/tests/test_attribute_set_mass_edit.py
odoo/addons/attribute_set_mass_edit/views/attribute_attribute.xml
odoo/addons/attribute_set_mass_edit/wizards/__init__.py
odoo/addons/attribute_set_mass_edit/wizards/mass_editing_wizard.py
odoo14_addon_attribute_set_mass_edit-14.0.1.1.0.dist-info/METADATA
odoo14_addon_attribute_set_mass_edit-14.0.1.1.0.dist-info/WHEEL
odoo14_addon_attribute_set_mass_edit-14.0.1.1.0.dist-info/top_level.txt
odoo14_addon_attribute_set_mass_edit-14.0.1.1.0.dist-info/RECORD
