Metadata-Version: 2.1
Name: odoo14-addon-attribute-set-mass-edit
Version: 14.0.1.1.0
Summary: Attribute Set Mass Edit
Home-page: https://github.com/OCA/odoo-pim
Author: ACSONE SA/NV,Odoo Community Association (OCA)
Author-email: support@odoo-community.org
License: AGPL-3
Platform: UNKNOWN
Classifier: Programming Language :: Python
Classifier: Framework :: Odoo
Classifier: License :: OSI Approved :: GNU Affero General Public License v3
Requires-Python: >=3.6
Requires-Dist: odoo14-addon-attribute-set
Requires-Dist: odoo14-addon-mass-editing
Requires-Dist: odoo14-addon-onchange-helper
Requires-Dist: odoo (<14.1dev,>=14.0a)
